pfunk/__init__.py
pfunk/cli.py
pfunk/client.py
pfunk/collection.py
pfunk/contrib/__init__.py
pfunk/contrib/auth/__init__.py
pfunk/contrib/auth/collections.py
pfunk/contrib/auth/resources.py
pfunk/contrib/auth/views.py
pfunk/contrib/ecommerce/__init__.py
pfunk/contrib/ecommerce/collections.py
pfunk/contrib/ecommerce/resources.py
pfunk/contrib/ecommerce/views.py
pfunk/contrib/email/__init__.py
pfunk/contrib/email/base.py
pfunk/contrib/email/ses.py
pfunk/contrib/generic.py
pfunk/contrib/templates.py
pfunk/exceptions.py
pfunk/fields.py
pfunk/project.py
pfunk/queryset.py
pfunk/resources.py
pfunk/template.py
pfunk/testcase.py
pfunk/tests/__init__.py
pfunk/tests/templates/auth/verification_email.html
pfunk/tests/templates/auth/verification_email.txt
pfunk/tests/templates/email/email_template.html
pfunk/tests/test_auth.py
pfunk/tests/test_collection.py
pfunk/tests/test_crud.py
pfunk/tests/test_deployment.py
pfunk/tests/test_email.py
pfunk/tests/test_jwt.py
pfunk/tests/test_project.py
pfunk/tests/test_resources.py
pfunk/tests/test_web_change_password.py
pfunk/tests/test_web_crud.py
pfunk/tests/test_web_forgot_password.py
pfunk/tests/test_web_login.py
pfunk/tests/test_web_signup.py
pfunk/tests/test_web_stripe.py
pfunk/utils/__init__.py
pfunk/utils/deploy.py
pfunk/utils/json_utils.py
pfunk/utils/publishing.py
pfunk/web/__init__.py
pfunk/web/request.py
pfunk/web/response.py
pfunk/web/views/__init__.py
pfunk/web/views/base.py
pfunk/web/views/graphql.py
pfunk/web/views/json.py
pfunk-0.5.12.dist-info/entry_points.txt
pfunk-0.5.12.dist-info/LICENSE
pfunk-0.5.12.dist-info/WHEEL
pfunk-0.5.12.dist-info/METADATA
pfunk-0.5.12.dist-info/RECORD
